odoo/addons/stock_inventory_preparation_filter_pos/README.rst
odoo/addons/stock_inventory_preparation_filter_pos/__init__.py
odoo/addons/stock_inventory_preparation_filter_pos/__manifest__.py
odoo/addons/stock_inventory_preparation_filter_pos/i18n/it.po
odoo/addons/stock_inventory_preparation_filter_pos/i18n/stock_inventory_preparation_filter_pos.pot
odoo/addons/stock_inventory_preparation_filter_pos/models/__init__.py
odoo/addons/stock_inventory_preparation_filter_pos/models/stock_inventory.py
odoo/addons/stock_inventory_preparation_filter_pos/readme/CONTRIBUTORS.rst
odoo/addons/stock_inventory_preparation_filter_pos/readme/DESCRIPTION.rst
odoo/addons/stock_inventory_preparation_filter_pos/readme/USAGE.rst
odoo/addons/stock_inventory_preparation_filter_pos/static/description/icon.png
odoo/addons/stock_inventory_preparation_filter_pos/static/description/index.html
odoo/addons/stock_inventory_preparation_filter_pos/tests/__init__.py
odoo/addons/stock_inventory_preparation_filter_pos/tests/test_preparation_filter_pos.py
odoo/addons/stock_inventory_preparation_filter_pos/views/stock_inventory.xml
odoo14_addon_stock_inventory_preparation_filter_pos-14.0.1.0.1.dev6.dist-info/METADATA
odoo14_addon_stock_inventory_preparation_filter_pos-14.0.1.0.1.dev6.dist-info/WHEEL
odoo14_addon_stock_inventory_preparation_filter_pos-14.0.1.0.1.dev6.dist-info/top_level.txt
odoo14_addon_stock_inventory_preparation_filter_pos-14.0.1.0.1.dev6.dist-info/RECORD
